wraplite/__init__.py
wraplite/__version__.py
wraplite/database.py
wraplite/exceptions.py
wraplite/table.py
wraplite-0.1.1.dist-info/LICENSE
wraplite-0.1.1.dist-info/METADATA
wraplite-0.1.1.dist-info/WHEEL
wraplite-0.1.1.dist-info/top_level.txt
wraplite-0.1.1.dist-info/RECORD
